{
	"elements": [
		{
			"data": {
				"Category": "harmful",
				"Color": 2445989,
				"Instant": false
			},
			"weight": 1.0,
			"key": "netherexp:absorption_immunity"
		},
		{
			"data": {
				"Category": "neutral",
				"Color": 11730944,
				"Instant": false
			},
			"weight": 1.0,
			"key": "netherexp:betrayed"
		},
		{
			"data": {
				"Category": "beneficial",
				"Color": 7235236,
				"Instant": false
			},
			"weight": 1.0,
			"key": "netherexp:brain_damage_immunity"
		},
		{
			"data": {
				"Category": "beneficial",
				"Color": 2696993,
				"Instant": false
			},
			"weight": 1.0,
			"key": "netherexp:darkness_immunity"
		},
		{
			"data": {
				"Category": "harmful",
				"Color": 16750848,
				"Instant": false
			},
			"weight": 1.0,
			"key": "netherexp:fire_resistance_immunity"
		},
		{
			"data": {
				"Category": "beneficial",
				"Color": 6497843,
				"Instant": false
			},
			"weight": 1.0,
			"key": "netherexp:fogsight"
		},
		{
			"data": {
				"Category": "harmful",
				"Color": 14270531,
				"Instant": false
			},
			"weight": 1.0,
			"key": "netherexp:haste_immunity"
		},
		{
			"data": {
				"Category": "beneficial",
				"Color": 5797459,
				"Instant": false
			},
			"weight": 1.0,
			"key": "netherexp:hunger_immunity"
		},
		{
			"data": {
				"Category": "harmful",
				"Color": 16185078,
				"Instant": false
			},
			"weight": 1.0,
			"key": "netherexp:invisibility_immunity"
		},
		{
			"data": {
				"Category": "harmful",
				"Color": 16646020,
				"Instant": false
			},
			"weight": 1.0,
			"key": "netherexp:jump_boost_immunity"
		},
		{
			"data": {
				"Category": "beneficial",
				"Color": 13565951,
				"Instant": false
			},
			"weight": 1.0,
			"key": "netherexp:levitation_immunity"
		},
		{
			"data": {
				"Category": "harmful",
				"Color": 5882118,
				"Instant": false
			},
			"weight": 1.0,
			"key": "netherexp:luck_immunity"
		},
		{
			"data": {
				"Category": "beneficial",
				"Color": 4866583,
				"Instant": false
			},
			"weight": 1.0,
			"key": "netherexp:mining_fatigue_immunity"
		},
		{
			"data": {
				"Category": "beneficial",
				"Color": 8889187,
				"Instant": false
			},
			"weight": 1.0,
			"key": "netherexp:poison_immunity"
		},
		{
			"data": {
				"Category": "harmful",
				"Color": 13458603,
				"Instant": false
			},
			"weight": 1.0,
			"key": "netherexp:regeneration_immunity"
		},
		{
			"data": {
				"Category": "harmful",
				"Color": 9520880,
				"Instant": false
			},
			"weight": 1.0,
			"key": "netherexp:resistance_immunity"
		},
		{
			"data": {
				"Category": "beneficial",
				"Color": 9154528,
				"Instant": false
			},
			"weight": 1.0,
			"key": "netherexp:slowness_immunity"
		},
		{
			"data": {
				"Category": "harmful",
				"Color": 3402751,
				"Instant": false
			},
			"weight": 1.0,
			"key": "netherexp:speed_immunity"
		},
		{
			"data": {
				"Category": "harmful",
				"Color": 16762624,
				"Instant": false
			},
			"weight": 1.0,
			"key": "netherexp:strength_immunity"
		},
		{
			"data": {
				"Category": "beneficial",
				"Color": 1787717,
				"Instant": false
			},
			"weight": 1.0,
			"key": "netherexp:unbounded_speed"
		},
		{
			"data": {
				"Category": "beneficial",
				"Color": 12624973,
				"Instant": false
			},
			"weight": 1.0,
			"key": "netherexp:unluck_immunity"
		},
		{
			"data": {
				"Category": "harmful",
				"Color": 10017472,
				"Instant": false
			},
			"weight": 1.0,
			"key": "netherexp:water_breathing_immunity"
		},
		{
			"data": {
				"Category": "beneficial",
				"Color": 4738376,
				"Instant": false
			},
			"weight": 1.0,
			"key": "netherexp:weakness_immunity"
		},
		{
			"data": {
				"Category": "beneficial",
				"Color": 7561558,
				"Instant": false
			},
			"weight": 1.0,
			"key": "netherexp:wither_immunity"
		}
	]
}
