{
	"elements": [
		{
			"data": {
				"Type": "block"
			},
			"weight": 1.0,
			"key": "blocks/alder_button"
		},
		{
			"data": {
				"Type": "block"
			},
			"weight": 1.0,
			"key": "blocks/alder_fence"
		},
		{
			"data": {
				"Type": "block"
			},
			"weight": 1.0,
			"key": "blocks/alder_fence_gate"
		},
		{
			"data": {
				"Type": "block"
			},
			"weight": 1.0,
			"key": "blocks/alder_leaves"
		},
		{
			"data": {
				"Type": "block"
			},
			"weight": 1.0,
			"key": "blocks/alder_log"
		},
		{
			"data": {
				"Type": "block"
			},
			"weight": 1.0,
			"key": "blocks/alder_planks"
		},
		{
			"data": {
				"Type": "block"
			},
			"weight": 1.0,
			"key": "blocks/alder_pressure_plate"
		},
		{
			"data": {
				"Type": "block"
			},
			"weight": 1.0,
			"key": "blocks/alder_sapling"
		},
		{
			"data": {
				"Type": "block"
			},
			"weight": 1.0,
			"key": "blocks/alder_slab"
		},
		{
			"data": {
				"Type": "block"
			},
			"weight": 1.0,
			"key": "blocks/alder_stairs"
		},
		{
			"data": {
				"Type": "block"
			},
			"weight": 1.0,
			"key": "blocks/altar"
		},
		{
			"data": {
				"Type": "block"
			},
			"weight": 1.0,
			"key": "blocks/belladonna"
		},
		{
			"data": {
				"Type": "block"
			},
			"weight": 1.0,
			"key": "blocks/blood_poppy"
		},
		{
			"data": {
				"Type": "block"
			},
			"weight": 1.0,
			"key": "blocks/candelabra"
		},
		{
			"data": {
				"Type": "block"
			},
			"weight": 1.0,
			"key": "blocks/chalice"
		},
		{
			"data": {
				"Type": "block"
			},
			"weight": 1.0,
			"key": "blocks/chalice_filled"
		},
		{
			"data": {
				"Type": "block"
			},
			"weight": 1.0,
			"key": "blocks/distillery"
		},
		{
			"data": {
				"Type": "block"
			},
			"weight": 1.0,
			"key": "blocks/ember_moss"
		},
		{
			"data": {
				"Type": "block"
			},
			"weight": 1.0,
			"key": "blocks/fume_funnel"
		},
		{
			"data": {
				"Type": "block"
			},
			"weight": 1.0,
			"key": "blocks/fume_funnel_filtered"
		},
		{
			"data": {
				"Type": "block"
			},
			"weight": 1.0,
			"key": "blocks/garlic"
		},
		{
			"data": {
				"Type": "block"
			},
			"weight": 1.0,
			"key": "blocks/glint_weed"
		},
		{
			"data": {
				"Type": "block"
			},
			"weight": 1.0,
			"key": "blocks/hawthorn_button"
		},
		{
			"data": {
				"Type": "block"
			},
			"weight": 1.0,
			"key": "blocks/hawthorn_fence"
		},
		{
			"data": {
				"Type": "block"
			},
			"weight": 1.0,
			"key": "blocks/hawthorn_fence_gate"
		},
		{
			"data": {
				"Type": "block"
			},
			"weight": 1.0,
			"key": "blocks/hawthorn_leaves"
		},
		{
			"data": {
				"Type": "block"
			},
			"weight": 1.0,
			"key": "blocks/hawthorn_log"
		},
		{
			"data": {
				"Type": "block"
			},
			"weight": 1.0,
			"key": "blocks/hawthorn_planks"
		},
		{
			"data": {
				"Type": "block"
			},
			"weight": 1.0,
			"key": "blocks/hawthorn_pressure_plate"
		},
		{
			"data": {
				"Type": "block"
			},
			"weight": 1.0,
			"key": "blocks/hawthorn_sapling"
		},
		{
			"data": {
				"Type": "block"
			},
			"weight": 1.0,
			"key": "blocks/hawthorn_slab"
		},
		{
			"data": {
				"Type": "block"
			},
			"weight": 1.0,
			"key": "blocks/hawthorn_stairs"
		},
		{
			"data": {
				"Type": "block"
			},
			"weight": 1.0,
			"key": "blocks/kettle"
		},
		{
			"data": {
				"Type": "block"
			},
			"weight": 1.0,
			"key": "blocks/mandrake"
		},
		{
			"data": {
				"Type": "block"
			},
			"weight": 1.0,
			"key": "blocks/poppet_shelf"
		},
		{
			"data": {
				"Type": "block"
			},
			"weight": 1.0,
			"key": "blocks/protection_barrier"
		},
		{
			"data": {
				"Type": "block"
			},
			"weight": 1.0,
			"key": "blocks/protection_barrier_temporary"
		},
		{
			"data": {
				"Type": "block"
			},
			"weight": 1.0,
			"key": "blocks/rowan_button"
		},
		{
			"data": {
				"Type": "block"
			},
			"weight": 1.0,
			"key": "blocks/rowan_fence"
		},
		{
			"data": {
				"Type": "block"
			},
			"weight": 1.0,
			"key": "blocks/rowan_fence_gate"
		},
		{
			"data": {
				"Type": "block"
			},
			"weight": 1.0,
			"key": "blocks/rowan_leaves"
		},
		{
			"data": {
				"Type": "block"
			},
			"weight": 1.0,
			"key": "blocks/rowan_log"
		},
		{
			"data": {
				"Type": "block"
			},
			"weight": 1.0,
			"key": "blocks/rowan_planks"
		},
		{
			"data": {
				"Type": "block"
			},
			"weight": 1.0,
			"key": "blocks/rowan_pressure_plate"
		},
		{
			"data": {
				"Type": "block"
			},
			"weight": 1.0,
			"key": "blocks/rowan_sapling"
		},
		{
			"data": {
				"Type": "block"
			},
			"weight": 1.0,
			"key": "blocks/rowan_slab"
		},
		{
			"data": {
				"Type": "block"
			},
			"weight": 1.0,
			"key": "blocks/rowan_stairs"
		},
		{
			"data": {
				"Type": "block"
			},
			"weight": 1.0,
			"key": "blocks/snowbell"
		},
		{
			"data": {
				"Type": "block"
			},
			"weight": 1.0,
			"key": "blocks/spanish_moss"
		},
		{
			"data": {
				"Type": "block"
			},
			"weight": 1.0,
			"key": "blocks/spinning_wheel"
		},
		{
			"data": {
				"Type": "block"
			},
			"weight": 1.0,
			"key": "blocks/stripped_alder_log"
		},
		{
			"data": {
				"Type": "block"
			},
			"weight": 1.0,
			"key": "blocks/stripped_hawthorn_log"
		},
		{
			"data": {
				"Type": "block"
			},
			"weight": 1.0,
			"key": "blocks/stripped_rowan_log"
		},
		{
			"data": {
				"Type": "block"
			},
			"weight": 1.0,
			"key": "blocks/water_artichoke"
		},
		{
			"data": {
				"Type": "block"
			},
			"weight": 1.0,
			"key": "blocks/wicker_bundle"
		},
		{
			"data": {
				"Type": "block"
			},
			"weight": 1.0,
			"key": "blocks/witch_cauldron"
		},
		{
			"data": {
				"Type": "block"
			},
			"weight": 1.0,
			"key": "blocks/witch_oven"
		},
		{
			"data": {
				"Type": "block"
			},
			"weight": 1.0,
			"key": "blocks/wolfsbane"
		},
		{
			"data": {
				"Type": "entity"
			},
			"weight": 1.0,
			"key": "entities/mandrake"
		},
		{
			"data": {
				"Type": "generic"
			},
			"weight": 1.0,
			"key": "extensions/blocks/grass_seeds"
		},
		{
			"data": {
				"Type": "generic"
			},
			"weight": 1.0,
			"key": "extensions/entities/bat"
		},
		{
			"data": {
				"Type": "generic"
			},
			"weight": 1.0,
			"key": "extensions/entities/creeper"
		},
		{
			"data": {
				"Type": "generic"
			},
			"weight": 1.0,
			"key": "extensions/entities/wolf"
		}
	]
}
