{
	"elements": [
		{
			"data": {
				"fluidName": "garnished:apple_cider"
			},
			"weight": 1.0,
			"key": "garnished:apple_cider"
		},
		{
			"data": {
				"fluidName": "garnished:black_mastic_resin"
			},
			"weight": 1.0,
			"key": "garnished:black_mastic_resin"
		},
		{
			"data": {
				"fluidName": "garnished:blue_mastic_resin"
			},
			"weight": 1.0,
			"key": "garnished:blue_mastic_resin"
		},
		{
			"data": {
				"fluidName": "garnished:brown_mastic_resin"
			},
			"weight": 1.0,
			"key": "garnished:brown_mastic_resin"
		},
		{
			"data": {
				"fluidName": "garnished:cashew_mixture"
			},
			"weight": 1.0,
			"key": "garnished:cashew_mixture"
		},
		{
			"data": {
				"fluidName": "garnished:cyan_mastic_resin"
			},
			"weight": 1.0,
			"key": "garnished:cyan_mastic_resin"
		},
		{
			"data": {
				"fluidName": "garnished:dragon_breath"
			},
			"weight": 1.0,
			"key": "garnished:dragon_breath"
		},
		{
			"data": {
				"fluidName": "garnished:garnish"
			},
			"weight": 1.0,
			"key": "garnished:garnish"
		},
		{
			"data": {
				"fluidName": "garnished:gray_mastic_resin"
			},
			"weight": 1.0,
			"key": "garnished:gray_mastic_resin"
		},
		{
			"data": {
				"fluidName": "garnished:green_mastic_resin"
			},
			"weight": 1.0,
			"key": "garnished:green_mastic_resin"
		},
		{
			"data": {
				"fluidName": "garnished:light_blue_mastic_resin"
			},
			"weight": 1.0,
			"key": "garnished:light_blue_mastic_resin"
		},
		{
			"data": {
				"fluidName": "garnished:light_gray_mastic_resin"
			},
			"weight": 1.0,
			"key": "garnished:light_gray_mastic_resin"
		},
		{
			"data": {
				"fluidName": "garnished:lime_mastic_resin"
			},
			"weight": 1.0,
			"key": "garnished:lime_mastic_resin"
		},
		{
			"data": {
				"fluidName": "garnished:magenta_mastic_resin"
			},
			"weight": 1.0,
			"key": "garnished:magenta_mastic_resin"
		},
		{
			"data": {
				"fluidName": "garnished:mastic_resin"
			},
			"weight": 1.0,
			"key": "garnished:mastic_resin"
		},
		{
			"data": {
				"fluidName": "garnished:orange_mastic_resin"
			},
			"weight": 1.0,
			"key": "garnished:orange_mastic_resin"
		},
		{
			"data": {
				"fluidName": "garnished:peanut_oil"
			},
			"weight": 1.0,
			"key": "garnished:peanut_oil"
		},
		{
			"data": {
				"fluidName": "garnished:pink_mastic_resin"
			},
			"weight": 1.0,
			"key": "garnished:pink_mastic_resin"
		},
		{
			"data": {
				"fluidName": "garnished:purple_mastic_resin"
			},
			"weight": 1.0,
			"key": "garnished:purple_mastic_resin"
		},
		{
			"data": {
				"fluidName": "garnished:red_mastic_resin"
			},
			"weight": 1.0,
			"key": "garnished:red_mastic_resin"
		},
		{
			"data": {
				"fluidName": "garnished:sweet_tea"
			},
			"weight": 1.0,
			"key": "garnished:sweet_tea"
		},
		{
			"data": {
				"fluidName": "garnished:white_mastic_resin"
			},
			"weight": 1.0,
			"key": "garnished:white_mastic_resin"
		},
		{
			"data": {
				"fluidName": "garnished:yellow_mastic_resin"
			},
			"weight": 1.0,
			"key": "garnished:yellow_mastic_resin"
		}
	]
}
